pulsar/__about__.pyi
pulsar/__init__.pyi
pulsar/asyncio.pyi
pulsar/exceptions.pyi
pulsar/functions/__init__.pyi
pulsar/functions/context.pyi
pulsar/functions/function.pyi
pulsar/functions/serde.pyi
pulsar/schema/__init__.pyi
pulsar/schema/definition.pyi
pulsar/schema/schema.pyi
pulsar/schema/schema_avro.pyi
pulsar_stubs-0.0.1.dev3.dist-info/METADATA
pulsar_stubs-0.0.1.dev3.dist-info/WHEEL
pulsar_stubs-0.0.1.dev3.dist-info/RECORD
