Metadata-Version: 2.4
Name: pulsar-stubs
Version: 0.0.1.dev3
Summary: A collection of the Apache Pulsar stub files.
Project-URL: Homepage, https://github.com/danchev/pulsar-stubs
Project-URL: Issues, https://github.com/danchev/pulsar-stubs/issues
Classifier: Development Status :: 4 - Beta
Classifier: Intended Audience :: Developers
Classifier: License :: OSI Approved :: Apache Software License
Classifier: Programming Language :: Python :: 3
Classifier: Programming Language :: Python :: 3 :: Only
Classifier: Programming Language :: Python :: Implementation :: CPython
Classifier: Programming Language :: Python :: Implementation :: PyPy
Classifier: Typing :: Typed
Requires-Python: >=3.12
Requires-Dist: pulsar-client>=3.6.0
